tgaflow/__init__.py
tgaflow/base.py
tgaflow/check.py
tgaflow/download.py
tgaflow/refresh.py
tgaflow/tasks.py
tgaflow/transfer.py
tgautil/__init__.py
tgautil/bloom_service.py
tgautil/dingtalk.py
tgautil/download_util.py
tgautil/sql_format.py
tga_tgautil-0.0.13.dist-info/LICENSE
tga_tgautil-0.0.13.dist-info/METADATA
tga_tgautil-0.0.13.dist-info/WHEEL
tga_tgautil-0.0.13.dist-info/top_level.txt
tga_tgautil-0.0.13.dist-info/RECORD
