Metadata-Version: 2.1
Name: tga tgautil
Version: 0.0.13
Summary: Some useful util tools for tga
Home-page: https://github.com/jewdore/tga-utils.git
Author: DSC Developer
Author-email: 1106896377@qq.com
License: UNKNOWN
Platform: UNKNOWN
Classifier: Programming Language :: Python :: 3
Classifier: License :: OSI Approved :: MIT License
Classifier: Operating System :: OS Independent
License-File: LICENSE
